proptool/__init__.py
proptool/app.py
proptool/config.py
proptool/config_builder.py
proptool/config_reader.py
proptool/config_reader_genbuild.py
proptool/const.py
proptool/entries.py
proptool/log.py
proptool/main.py
proptool/overrides.py
proptool/propfile.py
proptool/report.py
proptool/util.py
proptool/utils.py
proptool/utils2.py
proptool/check/__init__.py
proptool/check/brackets.py
proptool/check/check.py
proptool/check/dangling_keys.py
proptool/check/empty_translations.py
proptool/check/formatting_values.py
proptool/check/key_format.py
proptool/check/missing_keys.py
proptool/check/missing_translation.py
proptool/check/punctuation.py
proptool/check/quotation_marks.py
proptool/check/space_before_linefeed.py
proptool/check/starts_with_the_same_case.py
proptool/check/trailing_spaces.py
proptool/check/trailing_white_chars.py
proptool/check/trailing_whitechars.py
proptool/check/white_chars_before_linefeed.py
proptool/check/whitechars_before_linefeed.py
proptool/check/base/__init__.py
proptool/check/base/check.py
proptool/checks/__init__.py
proptool/checks/brackets.py
proptool/checks/dangling_keys.py
proptool/checks/empty_translations.py
proptool/checks/formatting_values.py
proptool/checks/key_format.py
proptool/checks/missing_translation.py
proptool/checks/missing_translations.py
proptool/checks/punctuation.py
proptool/checks/quotation_marks.py
proptool/checks/starts_with_the_same_case.py
proptool/checks/trailing_white_chars.py
proptool/checks/typesetting_quotation_marks.py
proptool/checks/white_chars_before_linefeed.py
proptool/checks/base/__init__.py
proptool/checks/base/check.py
proptool/config/__init__.py
proptool/config/builder.py
proptool/config/checker_info.py
proptool/config/config.py
proptool/config/config_builder.py
proptool/config/config_reader.py
proptool/config/reader.py
proptool/decorators/__init__.py
proptool/decorators/overrides.py
proptool/prop/__init__.py
proptool/prop/file.py
proptool/prop/items.py
proptool/report/__init__.py
proptool/report/error.py
prop_tool-2.0.0.dist-info/LICENSE.md
prop_tool-2.0.0.dist-info/METADATA
prop_tool-2.0.0.dist-info/WHEEL
prop_tool-2.0.0.dist-info/entry_points.txt
prop_tool-2.0.0.dist-info/top_level.txt
prop_tool-2.0.0.dist-info/RECORD
