Metadata-Version: 2.1
Name: prop-tool
Version: 2.0.0
Summary: prop-tool: Java *.properties file sync checker and syncing tool.
Home-page: https://github.com/MarcinOrlowski/prop-tool/
Author: Marcin Orlowski
Author-email: mail@marcinOrlowski.com
License: MIT License
Project-URL: Bug Tracker, https://github.com/MarcinOrlowski/prop-tool/issues/
Project-URL: Documentation, https://github.com/MarcinOrlowski/prop-tool/
Project-URL: Source Code, https://github.com/MarcinOrlowski/prop-tool/
Keywords: java properties sync check validation
Platform: UNKNOWN
Classifier: Programming Language :: Python :: 3
Classifier: License :: OSI Approved :: MIT License
Classifier: Operating System :: OS Independent
Requires-Python: >=3.6
Requires-Dist: argparse (>=1.4.0)
